{
  "radius": 4.86370325,
  "points": [
    {
      "x": -0.99999994,
      "y": -3.732051,
      "x0y": {
        "x": -0.99999994,
        "z": -3.732051,
        "normalized": {
          "x": -0.258819044,
          "z": -0.9659259,
          "xz": {
            "x": -0.258819044,
            "y": -0.9659259
          },
          "xy": {
            "x": -0.258819044,
            "x0y": {
              "x": -0.258819044,
              "normalized": {
                "x": -1.0,
                "xz": {
                  "x": -1.0
                },
                "xy": {
                  "x": -1.0
                },
                "noY": {
                  "x": -1.0
                }
              }
            }
          },
          "noY": {
            "x": -0.258819044,
            "y": -0.9659259
          }
        },
        "xy": {
          "x": -0.99999994,
          "x0y": {
            "x": -0.99999994,
            "normalized": {
              "x": -1.0,
              "xz": {
                "x": -1.0
              },
              "xy": {
                "x": -1.0
              },
              "noY": {
                "x": -1.0
              }
            }
          }
        }
      }
    },
    {
      "x": 0.99999994,
      "y": -3.732051,
      "x0y": {
        "x": 0.99999994,
        "z": -3.732051,
        "normalized": {
          "x": 0.258819044,
          "z": -0.9659259,
          "xz": {
            "x": 0.258819044,
            "y": -0.9659259
          },
          "xy": {
            "x": 0.258819044,
            "x0y": {
              "x": 0.258819044,
              "normalized": {
                "x": 1.0,
                "xz": {
                  "x": 1.0
                },
                "xy": {
                  "x": 1.0
                },
                "noY": {
                  "x": 1.0
                }
              }
            }
          },
          "noY": {
            "x": 0.258819044,
            "y": -0.9659259
          }
        },
        "xy": {
          "x": 0.99999994,
          "x0y": {
            "x": 0.99999994,
            "normalized": {
              "x": 1.0,
              "xz": {
                "x": 1.0
              },
              "xy": {
                "x": 1.0
              },
              "noY": {
                "x": 1.0
              }
            }
          }
        }
      }
    },
    {
      "x": -2.73205066,
      "y": -2.73205066,
      "x0y": {
        "x": -2.73205066,
        "z": -2.73205066,
        "normalized": {
          "x": -0.707106769,
          "z": -0.707106769,
          "normalized": {
            "x": -0.7071068,
            "z": -0.7071068,
            "xz": {
              "x": -0.7071068,
              "y": -0.7071068
            },
            "xy": {
              "x": -0.7071068,
              "x0y": {
                "x": -0.7071068,
                "normalized": {
                  "x": -1.0,
                  "xz": {
                    "x": -1.0
                  },
                  "xy": {
                    "x": -1.0
                  },
                  "noY": {
                    "x": -1.0
                  }
                }
              }
            },
            "noY": {
              "x": -0.7071068,
              "y": -0.7071068
            }
          },
          "xz": {
            "x": -0.707106769,
            "y": -0.707106769
          },
          "xy": {
            "x": -0.707106769,
            "x0y": {
              "x": -0.707106769,
              "normalized": {
                "x": -1.0,
                "xz": {
                  "x": -1.0
                },
                "xy": {
                  "x": -1.0
                },
                "noY": {
                  "x": -1.0
                }
              }
            }
          },
          "noY": {
            "x": -0.707106769,
            "y": -0.707106769
          }
        },
        "xy": {
          "x": -2.73205066,
          "x0y": {
            "x": -2.73205066,
            "normalized": {
              "x": -1.0,
              "xz": {
                "x": -1.0
              },
              "xy": {
                "x": -1.0
              },
              "noY": {
                "x": -1.0
              }
            }
          }
        }
      }
    },
    {
      "x": 2.73205066,
      "y": -2.73205066,
      "x0y": {
        "x": 2.73205066,
        "z": -2.73205066,
        "normalized": {
          "x": 0.707106769,
          "z": -0.707106769,
          "normalized": {
            "x": 0.7071068,
            "z": -0.7071068,
            "xz": {
              "x": 0.7071068,
              "y": -0.7071068
            },
            "xy": {
              "x": 0.7071068,
              "x0y": {
                "x": 0.7071068,
                "normalized": {
                  "x": 1.0,
                  "xz": {
                    "x": 1.0
                  },
                  "xy": {
                    "x": 1.0
                  },
                  "noY": {
                    "x": 1.0
                  }
                }
              }
            },
            "noY": {
              "x": 0.7071068,
              "y": -0.7071068
            }
          },
          "xz": {
            "x": 0.707106769,
            "y": -0.707106769
          },
          "xy": {
            "x": 0.707106769,
            "x0y": {
              "x": 0.707106769,
              "normalized": {
                "x": 1.0,
                "xz": {
                  "x": 1.0
                },
                "xy": {
                  "x": 1.0
                },
                "noY": {
                  "x": 1.0
                }
              }
            }
          },
          "noY": {
            "x": 0.707106769,
            "y": -0.707106769
          }
        },
        "xy": {
          "x": 2.73205066,
          "x0y": {
            "x": 2.73205066,
            "normalized": {
              "x": 1.0,
              "xz": {
                "x": 1.0
              },
              "xy": {
                "x": 1.0
              },
              "noY": {
                "x": 1.0
              }
            }
          }
        }
      }
    },
    {
      "x": -0.99999994,
      "y": -1.73205078,
      "x0y": {
        "x": -0.99999994,
        "z": -1.73205078,
        "normalized": {
          "x": -0.5,
          "z": -0.866025448,
          "xz": {
            "x": -0.5,
            "y": -0.866025448
          },
          "xy": {
            "x": -0.5,
            "x0y": {
              "x": -0.5,
              "normalized": {
                "x": -1.0,
                "xz": {
                  "x": -1.0
                },
                "xy": {
                  "x": -1.0
                },
                "noY": {
                  "x": -1.0
                }
              }
            }
          },
          "noY": {
            "x": -0.5,
            "y": -0.866025448
          }
        },
        "xy": {
          "x": -0.99999994,
          "x0y": {
            "x": -0.99999994,
            "normalized": {
              "x": -1.0,
              "xz": {
                "x": -1.0
              },
              "xy": {
                "x": -1.0
              },
              "noY": {
                "x": -1.0
              }
            }
          }
        }
      }
    },
    {
      "x": 0.99999994,
      "y": -1.73205078,
      "x0y": {
        "x": 0.99999994,
        "z": -1.73205078,
        "normalized": {
          "x": 0.5,
          "z": -0.866025448,
          "xz": {
            "x": 0.5,
            "y": -0.866025448
          },
          "xy": {
            "x": 0.5,
            "x0y": {
              "x": 0.5,
              "normalized": {
                "x": 1.0,
                "xz": {
                  "x": 1.0
                },
                "xy": {
                  "x": 1.0
                },
                "noY": {
                  "x": 1.0
                }
              }
            }
          },
          "noY": {
            "x": 0.5,
            "y": -0.866025448
          }
        },
        "xy": {
          "x": 0.99999994,
          "x0y": {
            "x": 0.99999994,
            "normalized": {
              "x": 1.0,
              "xz": {
                "x": 1.0
              },
              "xy": {
                "x": 1.0
              },
              "noY": {
                "x": 1.0
              }
            }
          }
        }
      }
    },
    {
      "x": -3.732051,
      "y": -0.99999994,
      "x0y": {
        "x": -3.732051,
        "z": -0.99999994,
        "normalized": {
          "x": -0.9659259,
          "z": -0.258819044,
          "xz": {
            "x": -0.9659259,
            "y": -0.258819044
          },
          "xy": {
            "x": -0.9659259,
            "x0y": {
              "x": -0.9659259,
              "normalized": {
                "x": -1.0,
                "xz": {
                  "x": -1.0
                },
                "xy": {
                  "x": -1.0
                },
                "noY": {
                  "x": -1.0
                }
              }
            }
          },
          "noY": {
            "x": -0.9659259,
            "y": -0.258819044
          }
        },
        "xy": {
          "x": -3.732051,
          "x0y": {
            "x": -3.732051,
            "normalized": {
              "x": -1.0,
              "xz": {
                "x": -1.0
              },
              "xy": {
                "x": -1.0
              },
              "noY": {
                "x": -1.0
              }
            }
          }
        }
      }
    },
    {
      "x": 3.732051,
      "y": -0.99999994,
      "x0y": {
        "x": 3.732051,
        "z": -0.99999994,
        "normalized": {
          "x": 0.9659259,
          "z": -0.258819044,
          "xz": {
            "x": 0.9659259,
            "y": -0.258819044
          },
          "xy": {
            "x": 0.9659259,
            "x0y": {
              "x": 0.9659259,
              "normalized": {
                "x": 1.0,
                "xz": {
                  "x": 1.0
                },
                "xy": {
                  "x": 1.0
                },
                "noY": {
                  "x": 1.0
                }
              }
            }
          },
          "noY": {
            "x": 0.9659259,
            "y": -0.258819044
          }
        },
        "xy": {
          "x": 3.732051,
          "x0y": {
            "x": 3.732051,
            "normalized": {
              "x": 1.0,
              "xz": {
                "x": 1.0
              },
              "xy": {
                "x": 1.0
              },
              "noY": {
                "x": 1.0
              }
            }
          }
        }
      }
    },
    {
      "x": -1.99999988,
      "x0y": {
        "x": -1.99999988,
        "normalized": {
          "x": -1.0,
          "xz": {
            "x": -1.0
          },
          "xy": {
            "x": -1.0
          },
          "noY": {
            "x": -1.0
          }
        }
      }
    },
    {
      "isZero": true
    },
    {
      "x": 1.99999988,
      "x0y": {
        "x": 1.99999988,
        "normalized": {
          "x": 1.0,
          "xz": {
            "x": 1.0
          },
          "xy": {
            "x": 1.0
          },
          "noY": {
            "x": 1.0
          }
        }
      }
    },
    {
      "x": -3.732051,
      "y": 0.99999994,
      "x0y": {
        "x": -3.732051,
        "z": 0.99999994,
        "normalized": {
          "x": -0.9659259,
          "z": 0.258819044,
          "xz": {
            "x": -0.9659259,
            "y": 0.258819044
          },
          "xy": {
            "x": -0.9659259,
            "x0y": {
              "x": -0.9659259,
              "normalized": {
                "x": -1.0,
                "xz": {
                  "x": -1.0
                },
                "xy": {
                  "x": -1.0
                },
                "noY": {
                  "x": -1.0
                }
              }
            }
          },
          "noY": {
            "x": -0.9659259,
            "y": 0.258819044
          }
        },
        "xy": {
          "x": -3.732051,
          "x0y": {
            "x": -3.732051,
            "normalized": {
              "x": -1.0,
              "xz": {
                "x": -1.0
              },
              "xy": {
                "x": -1.0
              },
              "noY": {
                "x": -1.0
              }
            }
          }
        }
      }
    },
    {
      "x": 3.732051,
      "y": 0.99999994,
      "x0y": {
        "x": 3.732051,
        "z": 0.99999994,
        "normalized": {
          "x": 0.9659259,
          "z": 0.258819044,
          "xz": {
            "x": 0.9659259,
            "y": 0.258819044
          },
          "xy": {
            "x": 0.9659259,
            "x0y": {
              "x": 0.9659259,
              "normalized": {
                "x": 1.0,
                "xz": {
                  "x": 1.0
                },
                "xy": {
                  "x": 1.0
                },
                "noY": {
                  "x": 1.0
                }
              }
            }
          },
          "noY": {
            "x": 0.9659259,
            "y": 0.258819044
          }
        },
        "xy": {
          "x": 3.732051,
          "x0y": {
            "x": 3.732051,
            "normalized": {
              "x": 1.0,
              "xz": {
                "x": 1.0
              },
              "xy": {
                "x": 1.0
              },
              "noY": {
                "x": 1.0
              }
            }
          }
        }
      }
    },
    {
      "x": -0.99999994,
      "y": 1.73205078,
      "x0y": {
        "x": -0.99999994,
        "z": 1.73205078,
        "normalized": {
          "x": -0.5,
          "z": 0.866025448,
          "xz": {
            "x": -0.5,
            "y": 0.866025448
          },
          "xy": {
            "x": -0.5,
            "x0y": {
              "x": -0.5,
              "normalized": {
                "x": -1.0,
                "xz": {
                  "x": -1.0
                },
                "xy": {
                  "x": -1.0
                },
                "noY": {
                  "x": -1.0
                }
              }
            }
          },
          "noY": {
            "x": -0.5,
            "y": 0.866025448
          }
        },
        "xy": {
          "x": -0.99999994,
          "x0y": {
            "x": -0.99999994,
            "normalized": {
              "x": -1.0,
              "xz": {
                "x": -1.0
              },
              "xy": {
                "x": -1.0
              },
              "noY": {
                "x": -1.0
              }
            }
          }
        }
      }
    },
    {
      "x": 0.99999994,
      "y": 1.73205078,
      "x0y": {
        "x": 0.99999994,
        "z": 1.73205078,
        "normalized": {
          "x": 0.5,
          "z": 0.866025448,
          "xz": {
            "x": 0.5,
            "y": 0.866025448
          },
          "xy": {
            "x": 0.5,
            "x0y": {
              "x": 0.5,
              "normalized": {
                "x": 1.0,
                "xz": {
                  "x": 1.0
                },
                "xy": {
                  "x": 1.0
                },
                "noY": {
                  "x": 1.0
                }
              }
            }
          },
          "noY": {
            "x": 0.5,
            "y": 0.866025448
          }
        },
        "xy": {
          "x": 0.99999994,
          "x0y": {
            "x": 0.99999994,
            "normalized": {
              "x": 1.0,
              "xz": {
                "x": 1.0
              },
              "xy": {
                "x": 1.0
              },
              "noY": {
                "x": 1.0
              }
            }
          }
        }
      }
    },
    {
      "x": -2.73205066,
      "y": 2.73205066,
      "x0y": {
        "x": -2.73205066,
        "z": 2.73205066,
        "normalized": {
          "x": -0.707106769,
          "z": 0.707106769,
          "normalized": {
            "x": -0.7071068,
            "z": 0.7071068,
            "xz": {
              "x": -0.7071068,
              "y": 0.7071068
            },
            "xy": {
              "x": -0.7071068,
              "x0y": {
                "x": -0.7071068,
                "normalized": {
                  "x": -1.0,
                  "xz": {
                    "x": -1.0
                  },
                  "xy": {
                    "x": -1.0
                  },
                  "noY": {
                    "x": -1.0
                  }
                }
              }
            },
            "noY": {
              "x": -0.7071068,
              "y": 0.7071068
            }
          },
          "xz": {
            "x": -0.707106769,
            "y": 0.707106769
          },
          "xy": {
            "x": -0.707106769,
            "x0y": {
              "x": -0.707106769,
              "normalized": {
                "x": -1.0,
                "xz": {
                  "x": -1.0
                },
                "xy": {
                  "x": -1.0
                },
                "noY": {
                  "x": -1.0
                }
              }
            }
          },
          "noY": {
            "x": -0.707106769,
            "y": 0.707106769
          }
        },
        "xy": {
          "x": -2.73205066,
          "x0y": {
            "x": -2.73205066,
            "normalized": {
              "x": -1.0,
              "xz": {
                "x": -1.0
              },
              "xy": {
                "x": -1.0
              },
              "noY": {
                "x": -1.0
              }
            }
          }
        }
      }
    },
    {
      "x": 2.73205066,
      "y": 2.73205066,
      "x0y": {
        "x": 2.73205066,
        "z": 2.73205066,
        "normalized": {
          "x": 0.707106769,
          "z": 0.707106769,
          "normalized": {
            "x": 0.7071068,
            "z": 0.7071068,
            "xz": {
              "x": 0.7071068,
              "y": 0.7071068
            },
            "xy": {
              "x": 0.7071068,
              "x0y": {
                "x": 0.7071068,
                "normalized": {
                  "x": 1.0,
                  "xz": {
                    "x": 1.0
                  },
                  "xy": {
                    "x": 1.0
                  },
                  "noY": {
                    "x": 1.0
                  }
                }
              }
            },
            "noY": {
              "x": 0.7071068,
              "y": 0.7071068
            }
          },
          "xz": {
            "x": 0.707106769,
            "y": 0.707106769
          },
          "xy": {
            "x": 0.707106769,
            "x0y": {
              "x": 0.707106769,
              "normalized": {
                "x": 1.0,
                "xz": {
                  "x": 1.0
                },
                "xy": {
                  "x": 1.0
                },
                "noY": {
                  "x": 1.0
                }
              }
            }
          },
          "noY": {
            "x": 0.707106769,
            "y": 0.707106769
          }
        },
        "xy": {
          "x": 2.73205066,
          "x0y": {
            "x": 2.73205066,
            "normalized": {
              "x": 1.0,
              "xz": {
                "x": 1.0
              },
              "xy": {
                "x": 1.0
              },
              "noY": {
                "x": 1.0
              }
            }
          }
        }
      }
    },
    {
      "x": -0.99999994,
      "y": 3.732051,
      "x0y": {
        "x": -0.99999994,
        "z": 3.732051,
        "normalized": {
          "x": -0.258819044,
          "z": 0.9659259,
          "xz": {
            "x": -0.258819044,
            "y": 0.9659259
          },
          "xy": {
            "x": -0.258819044,
            "x0y": {
              "x": -0.258819044,
              "normalized": {
                "x": -1.0,
                "xz": {
                  "x": -1.0
                },
                "xy": {
                  "x": -1.0
                },
                "noY": {
                  "x": -1.0
                }
              }
            }
          },
          "noY": {
            "x": -0.258819044,
            "y": 0.9659259
          }
        },
        "xy": {
          "x": -0.99999994,
          "x0y": {
            "x": -0.99999994,
            "normalized": {
              "x": -1.0,
              "xz": {
                "x": -1.0
              },
              "xy": {
                "x": -1.0
              },
              "noY": {
                "x": -1.0
              }
            }
          }
        }
      }
    },
    {
      "x": 0.99999994,
      "y": 3.732051,
      "x0y": {
        "x": 0.99999994,
        "z": 3.732051,
        "normalized": {
          "x": 0.258819044,
          "z": 0.9659259,
          "xz": {
            "x": 0.258819044,
            "y": 0.9659259
          },
          "xy": {
            "x": 0.258819044,
            "x0y": {
              "x": 0.258819044,
              "normalized": {
                "x": 1.0,
                "xz": {
                  "x": 1.0
                },
                "xy": {
                  "x": 1.0
                },
                "noY": {
                  "x": 1.0
                }
              }
            }
          },
          "noY": {
            "x": 0.258819044,
            "y": 0.9659259
          }
        },
        "xy": {
          "x": 0.99999994,
          "x0y": {
            "x": 0.99999994,
            "normalized": {
              "x": 1.0,
              "xz": {
                "x": 1.0
              },
              "xy": {
                "x": 1.0
              },
              "noY": {
                "x": 1.0
              }
            }
          }
        }
      }
    }
  ]
}